[
  { "word": "НОЙ", "category": "Персонаж", "hint": "Один праведник и деревянный корабль против гнева небес." },
  { "word": "ДАВИД", "category": "Персонаж", "hint": "Пять гладких камней из ручья против медного шлема и копья." },
  { "word": "МОИСЕЙ", "category": "Персонаж", "hint": "Куст горел, но не сгорал, призывая его к великому освобождению." },
  { "word": "ИОНА", "category": "Персонаж", "hint": "Шторм утих, когда он скрылся во тьме морского гиганта." },
  { "word": "ИОСИФ", "category": "Персонаж", "hint": "Пестрые одежды привели к рабству, а сны — к власти." },
  { "word": "ПЁТР", "category": "Персонаж", "hint": "Шаг на волны требовал веры, но сомнение принесло страх." },
  { "word": "ПАВЕЛ", "category": "Персонаж", "hint": "Свет на пути в Дамаск превратил гонителя в проповедника." },
  { "word": "МАРИЯ", "category": "Персонаж", "hint": "Её сердце сохранило слова ангела о младенце." },
  { "word": "МАРФА", "category": "Персонаж", "hint": "Суета о многом заслонила для неё главное, пока она принимала Гостя." },
  { "word": "ЛАЗАРЬ", "category": "Персонаж", "hint": "Четыре дня в гробнице закончились словом: «Выйди вон!»" },
  { "word": "РУФЬ", "category": "Персонаж", "hint": "Колосья на чужом поле стали началом царской родословной." },
  { "word": "ЕСФИРЬ", "category": "Персонаж", "hint": "Молчание могло погубить народ, но смелость перед царем спасла всех." },
  { "word": "ВИФЛЕЕМ", "category": "Город", "hint": "Мал среди городов, но велик тем, кто в нем родился." },
  { "word": "НАЗАРЕТ", "category": "Город", "hint": "«Может ли отсюда быть что доброе?» — спрашивали о городе Его юности." },
  { "word": "ИЕРИХОН", "category": "Город", "hint": "Семь дней молчания и один крик разрушили непреступные стены." },
  { "word": "ИЕРУСАЛИМ", "category": "Город", "hint": "Город великого Царя, где завеса в святилище разорвалась надвое." },
  { "word": "ГАЛИЛЕЯ", "category": "Место", "hint": "Берега этого моря слышали больше притч, чем дворцы." },
  { "word": "СИНАЙ", "category": "Место", "hint": "Гора в дыму и огне, где слова были высечены на камне." },
  { "word": "КОВЧЕГ", "category": "Предмет", "hint": "Убежище, омытое водами очищения." },
  { "word": "СВИТОК", "category": "Предмет", "hint": "Слова пророков хранились на нем, разворачиваясь для чтения." },
  { "word": "ПРАЩА", "category": "Предмет", "hint": "Орудие пастуха, ставшее спасением для целого войска." },
  { "word": "АРФА", "category": "Предмет", "hint": "Её струны успокаивали мятежный дух первого царя." },
  { "word": "ПОСОХ", "category": "Предмет", "hint": "Опора в пути и знак власти над разделенным морем." },
  { "word": "МАННА", "category": "Символ", "hint": "Утренний хлеб, тающий под лучами солнца." },
  { "word": "СВЕТИЛЬНИК", "category": "Символ", "hint": "Тьма отступает там, где он зажжен от чистого масла." },
  { "word": "ЗАВЕТ", "category": "Понятие", "hint": "Кровь и обещание связали две стороны навеки." },
  { "word": "ВЕРА", "category": "Понятие", "hint": "Шаг в пустоту с уверенностью, что там есть твердая почва." },
  { "word": "МИЛОСТЬ", "category": "Понятие", "hint": "Когда закон требует наказания, она дарует прощение." },
  { "word": "БЛАГОДАТЬ", "category": "Понятие", "hint": "Сокровище, которое нельзя заслужить, но можно только принять." },
  { "word": "МОЛИТВА", "category": "Понятие", "hint": "Дыхание души, устремленное к небесам." },
  { "word": "ПРИТЧА", "category": "Жанр", "hint": "Земная история, скрывающая небесную тайну." },
  { "word": "ПСАЛОМ", "category": "Книга/жанр", "hint": "Стихи, в которых звучат слезы, покаяние и хвала." },
  { "word": "ИСХОД", "category": "Книга", "hint": "Путь от рабства к свободе через воды и пустыню." },
  { "word": "БЫТИЕ", "category": "Книга", "hint": "Начало всего, когда свет отделился от тьмы." },
  { "word": "ПРИТЧИ", "category": "Книга", "hint": "Собрание мудрости, где глупость называет себя громко." },
  { "word": "ЕВАНГЕЛИЕ", "category": "Понятие", "hint": "Добрая весть, изменившая ход истории навсегда." },
  { "word": "АПОСТОЛ", "category": "Понятие", "hint": "Тот, кто был послан нести свет до краев земли." },
  { "word": "ПУСТЫНЯ", "category": "Место", "hint": "Место испытаний и долгих странствий перед обетованием." },
  { "word": "ХРАМ", "category": "Место", "hint": "Дом, где облако славы однажды наполнило святое место." },
  { "word": "ЖЕРТВЕННИК", "category": "Предмет", "hint": "Камни, на которых огонь с небес поглощал приношения." }
]
